main.py
doeflow-0.0.1.dist-info/METADATA
doeflow-0.0.1.dist-info/WHEEL
doeflow-0.0.1.dist-info/top_level.txt
doeflow-0.0.1.dist-info/RECORD
