Metadata-Version: 2.4
Name: doeflow
Version: 0.0.1
Summary: Design of Experiments Workflow
Requires-Python: >=3.10
